whru/__init__.py
whru/log/__init__.py
whru/log/log.py
whru/tensorboard/__init__.py
whru/tensorboard/log.py
whru/tensorboard/read.py
whru/tensorboard/write.py
whru/utils/__init__.py
whru/utils/checkpoint.py
whru/utils/path.py
whru/utils/producer_consumer.py
whru/utils/utils.py
whru-0.4.1.dist-info/METADATA
whru-0.4.1.dist-info/WHEEL
whru-0.4.1.dist-info/top_level.txt
whru-0.4.1.dist-info/RECORD
